stratio/__init__.py
stratio/api/__init__.py
stratio/api/base_cluster_client.py
stratio/api/base_customer_client.py
stratio/api/base_keos_client.py
stratio/api/base_logs_client.py
stratio/api/base_operations_client.py
stratio/api/base_repositories_client.py
stratio/api/callbacks/__init__.py
stratio/api/callbacks/progress.py
stratio/api/cluster_client.py
stratio/api/customer_client.py
stratio/api/filters/__init__.py
stratio/api/filters/customer_filters.py
stratio/api/formatters/__init__.py
stratio/api/formatters/base_formatter.py
stratio/api/formatters/bootstrap_formatters.py
stratio/api/formatters/cluster_formatters.py
stratio/api/formatters/customer_formatters.py
stratio/api/keos_client.py
stratio/api/logs_client.py
stratio/api/models/__init__.py
stratio/api/models/bootstrap.py
stratio/api/models/cluster.py
stratio/api/models/customer.py
stratio/api/models/logs.py
stratio/api/models/repositories.py
stratio/api/operations_client.py
stratio/api/repositories_client.py
stratio/api/session/__init__.py
stratio/api/session/sessions.py
stratio/api/transformers/__init__.py
stratio/api/transformers/customer_result_parser.py
stratio/cli/__init__.py
stratio/cli/config.py
stratio/cli/config_default.yaml
stratio/cli/marketplace.py
stratio/cli/utils.py
stratio/config/__init__.py
stratio/config/clusters_config.py
stratio/config/config.py
stratio/config/customer_config.py
stratio/config/sessions_config.py
stratio/config/universe_config.py
stratio/utils/__init__.py
stratio/utils/commons.py
aws_marketplace_toolkit-0.1.9.dist-info/METADATA
aws_marketplace_toolkit-0.1.9.dist-info/WHEEL
aws_marketplace_toolkit-0.1.9.dist-info/entry_points.txt
aws_marketplace_toolkit-0.1.9.dist-info/RECORD
