Metadata-Version: 2.1
Name: aws-marketplace-toolkit
Version: 0.1.9
Summary: A CLI tool for managing Stratio AWS Marketplace clusters.
Home-page: https://github.com/Stratio/aws-marketplace-toolkit
License: MIT
Author: Stratio
Author-email: platform@stratio.com
Requires-Python: >=3.12,<4.0
Classifier: License :: OSI Approved :: MIT License
Classifier: Operating System :: OS Independent
Classifier: Programming Language :: Python :: 3
Classifier: Programming Language :: Python :: 3.12
Classifier: Programming Language :: Python :: 3.13
Requires-Dist: PyYAML (==6.0.2)
Requires-Dist: ansible-vault (==2.1.0)
Requires-Dist: awscli (==1.33.44)
Requires-Dist: boto3 (>=1.34.0,<1.35.0)
Requires-Dist: colorama (==0.4.6)
Requires-Dist: jq (==1.8.0)
Requires-Dist: packaging
Requires-Dist: pydantic (==2.10.3)
Requires-Dist: pyperclip (==1.9.0)
Requires-Dist: requests
Requires-Dist: rich (==13.9.3)
Requires-Dist: tabulate (==0.9.0)
Requires-Dist: tqdm (>=4.64.0)
Requires-Dist: typer (==0.15.1)
Requires-Dist: wheel (==0.44.0)
